{
  "layout": "blog",
  "title": "Taste",
  "date": "2020-02-06T21:03:10.138Z",
  "thumbnail": "/images/mcneil-headshot.jpeg",
  "body": "# It's time to talk about taste.\n\n## That's what I said, \"Taste.\"\n\nThere are three things you need to understand before you can move forward in thinkignab out taste. The first is clear, but the second and third bear a little more explanation that you might usually find on someone els'es blog. They are: \n\n1. You need to have a mouth first above all eslse\n2. You also need other things\n\nOk so let's move on to some bullet points\n\n* Yes\n* No\n\nPeace. It's easy to understand.\n\n>",
  "author": "Alex McNeil"
}